{"twitchData":{"id":"75045296","login":"juliestrator","display_name":"Juliestrator","type":"","broadcaster_type":"partner","description":"Join me on my education journey! Here I learn things I've always found exciting like 3d modelling, programming, game design etc.","profile_image_url":"https://static-cdn.jtvnw.net/jtv_user_pictures/93cae27a-fd63-487e-b2c7-fffbd29cf4a7-profile_image-300x300.png","offline_image_url":"https://static-cdn.jtvnw.net/jtv_user_pictures/3eea543e-ed15-411a-ad73-0d6f2039e7cb-channel_offline_image-1920x1080.jpeg","view_count":553299,"created_at":"2014-11-12T19:45:49.659015Z"},"streamData":{"id":"1080226244","stream_id":"42576657228","user_id":"75045296","user_login":"juliestrator","user_name":"Juliestrator","title":"New York diorama","description":"","created_at":"2021-07-08T08:22:43Z","published_at":"2021-07-08T08:22:43Z","url":"https://www.twitch.tv/videos/1080226244","thumbnail_url":"https://static-cdn.jtvnw.net/cf_vods/dgeft87wbj63p/7d6b963aba0d40d1e822_juliestrator_42576657228_1625732551//thumb/thumb0-%{width}x%{height}.jpg","viewable":"public","view_count":4,"language":"en","type":"archive","duration":"3h9m20s","muted_segments":null}}